airflow/providers/microsoft/__init__.py
airflow/providers/microsoft/fabric/__init__.py
airflow/providers/microsoft/fabric/get_provider_info.py
airflow/providers/microsoft/fabric/hooks/__init__.py
airflow/providers/microsoft/fabric/hooks/fabric.py
airflow/providers/microsoft/fabric/operators/__init__.py
airflow/providers/microsoft/fabric/operators/fabric.py
airflow/providers/microsoft/fabric/plugins/fabric.py.py
airflow/providers/microsoft/fabric/triggers/__init__.py
airflow/providers/microsoft/fabric/triggers/fabric.py
apache_airflow_providers_microsoft_fabric-1.0.3.dist-info/licenses/LICENSE
apache_airflow_providers_microsoft_fabric-1.0.3.dist-info/METADATA
apache_airflow_providers_microsoft_fabric-1.0.3.dist-info/WHEEL
apache_airflow_providers_microsoft_fabric-1.0.3.dist-info/entry_points.txt
apache_airflow_providers_microsoft_fabric-1.0.3.dist-info/top_level.txt
apache_airflow_providers_microsoft_fabric-1.0.3.dist-info/RECORD
