Metadata-Version: 2.4
Name: apache-airflow-providers-microsoft-fabric
Version: 1.0.3
Summary: A plugin for Apache Airflow to interact with Microsoft Fabric items
Author-email: Vinicius Fontes <vfontes@microsot.com>
Project-URL: Homepage, https://github.com/microsoft/apache-airflow-microsoft-fabric-plugin.git
Classifier: Programming Language :: Python :: 3
Classifier: Development Status :: 3 - Alpha
Classifier: Environment :: Plugins
Classifier: Intended Audience :: Developers
Classifier: Topic :: Software Development :: Libraries :: Python Modules
Requires-Python: >=3.8
License-File: LICENSE
Dynamic: license-file
